GIO/GIOKL.py
GIO/GIO_super.py
GIO/__init__.py
GIO/generate_text_embeddings.py
grad_info_opt-0.1.2.dist-info/LICENSE
grad_info_opt-0.1.2.dist-info/METADATA
grad_info_opt-0.1.2.dist-info/WHEEL
grad_info_opt-0.1.2.dist-info/top_level.txt
grad_info_opt-0.1.2.dist-info/RECORD
