Metadata-Version: 2.1
Name: grad-info-opt
Version: 0.1.2
Summary: Implementation of Gradient Information Optimization for efficient and scalable training data selection
Home-page: https://github.com/daeveraert/gradient-information-optimization
Author: Dante Everaert
Author-email: dante.everaert@berkeley.edu
Project-URL: Bug Tracker, https://github.com/daeveraert/gradient-information-optimization/issues
Classifier: Programming Language :: Python :: 3
Classifier: License :: OSI Approved :: Apache Software License
Classifier: Operating System :: OS Independent
Requires-Python: >=3.6
License-File: LICENSE
Requires-Dist: jax (>=0.3.25)
Requires-Dist: pyspark (>=2.4.8)
Requires-Dist: numpy (>=1.21.6)
Requires-Dist: sentence-transformers (>=2.2.2)
Requires-Dist: jaxlib (>=0.3.2)
Requires-Dist: pandas (>=1.0.5)
